django_toon/__init__.py
django_toon/parser.py
django_toon/render.py
django_toon/status.py
django_toon-0.1.1.dist-info/licenses/LICENSE
django_toon_cli/__init__.py
django_toon_cli/main.py
django_toon-0.1.1.dist-info/METADATA
django_toon-0.1.1.dist-info/WHEEL
django_toon-0.1.1.dist-info/entry_points.txt
django_toon-0.1.1.dist-info/top_level.txt
django_toon-0.1.1.dist-info/RECORD
