Metadata-Version: 2.4
Name: django-toon
Version: 0.1.1
Summary: django-toon is a package for sending data in the Toon format
Author-email: Ehsan Amiri <ehsan.amiri.prog@email.com>
License-Expression: MIT
Project-URL: Homepage, https://github.com/ehs22n/django-toon
Project-URL: Repository, https://github.com/ehs22n/django-toon
Classifier: Framework :: Django
Classifier: Programming Language :: Python :: 3
Requires-Python: >=3.10
License-File: LICENSE
Requires-Dist: python-toon>=0.1.3
Requires-Dist: djangorestframework>=3.14
Requires-Dist: typer>=0.21.0
Requires-Dist: requests>=2.32.5
Dynamic: license-file
